yc_managed_ytsaurus_auth/__init__.py
ytsaurus_client_yc_auth-0.1.0.dist-info/METADATA
ytsaurus_client_yc_auth-0.1.0.dist-info/WHEEL
ytsaurus_client_yc_auth-0.1.0.dist-info/top_level.txt
ytsaurus_client_yc_auth-0.1.0.dist-info/RECORD
