Metadata-Version: 2.4
Name: ytsaurus-client-yc-auth
Version: 0.1.0
Summary: Yandex Cloud auth for YTsaurus client
Author: Yandex LLC
Author-email: cloud@support.yandex.ru
License: Apache-2.0
Classifier: Programming Language :: Python
Classifier: Programming Language :: Python :: 3.8
Classifier: Programming Language :: Python :: 3.9
Classifier: Programming Language :: Python :: 3.10
Classifier: Programming Language :: Python :: 3.11
Classifier: License :: OSI Approved :: Apache Software License
Requires-Python: >=3.8
Requires-Dist: ytsaurus-client<0.14.0,>=0.13.33
Dynamic: author
Dynamic: author-email
Dynamic: classifier
Dynamic: description
Dynamic: description-content-type
Dynamic: license
Dynamic: requires-dist
Dynamic: requires-python
Dynamic: summary
